mylistanalyzer/__init__.py
mylistanalyzer/blueprint.py
mylistanalyzer/mla_core.py
mylistanalyzer/types.py
mylistanalyzer/utils.py
mylistanalyzer-0.1.2.dist-info/METADATA
mylistanalyzer-0.1.2.dist-info/WHEEL
mylistanalyzer-0.1.2.dist-info/RECORD
