Metadata-Version: 2.1
Name: mylistanalyzer
Version: 0.1.2
Summary: package to fetch and conduct ETL on your anime list from myanimelist
License: MIT
Author: Rahul
Author-email: saihanumarahul66@gmail.com
Requires-Python: >=3.12,<4.0
Classifier: License :: OSI Approved :: MIT License
Classifier: Programming Language :: Python :: 3
Classifier: Programming Language :: Python :: 3.12
Requires-Dist: lxml (>=5.2.2,<6.0.0)
